global_parser/__init__.py
global_parser/core.py
global_parser/exceptions.py
global_parser/file_parser/__init__.py
global_parser/file_parser/type/__init__.py
global_parser/file_parser/type/audio.py
global_parser/file_parser/type/file.py
global_parser/file_parser/type/image.py
global_parser/url_parser/__init__.py
global_parser/url_parser/parser.py
global_parser/utils/__init__.py
global_parser/utils/paragraph.py
global_parser/utils/sustainability_hf.py
global_parser/utils/upload.py
global_parser/utils/validSentence.py
global_parser_lib-0.1.8.dist-info/METADATA
global_parser_lib-0.1.8.dist-info/WHEEL
global_parser_lib-0.1.8.dist-info/top_level.txt
global_parser_lib-0.1.8.dist-info/RECORD
